tesh/__init__.py
tesh/changedir.py
tesh/extract.py
tesh/test.py
tesh/tests/__init__.py
tesh/tests/fixtures/debug.md
tesh/tests/fixtures/empty_folder/.gitkeep
tesh/tests/fixtures/exitcodes.md
tesh/tests/fixtures/exitcodes_multipleblocks.md
tesh/tests/fixtures/fail.md
tesh/tests/fixtures/fixture.md
tesh/tests/fixtures/folder/simple.md
tesh/tests/fixtures/long_command.md
tesh/tests/fixtures/multiline_command.md
tesh/tests/fixtures/multiple_codeblocks.md
tesh/tests/fixtures/no_codeblocks.md
tesh/tests/fixtures/prompt.md
tesh/tests/fixtures/setup.md
tesh/tests/fixtures/setup.sh
tesh/tests/fixtures/setup_fail.md
tesh/tests/fixtures/timeout.md
tesh/tests/fixtures/whitespace.md
tesh/tests/fixtures/wildcards.md
tesh/tests/test_extract.py
tesh/tests/test_tesh.py
tesh-0.3.2.dist-info/LICENSE
tesh-0.3.2.dist-info/METADATA
tesh-0.3.2.dist-info/WHEEL
tesh-0.3.2.dist-info/entry_points.txt
tesh-0.3.2.dist-info/RECORD
