Metadata-Version: 2.1
Name: tesh
Version: 0.3.2
Summary: TEstable SHell sessions in Markdown
License: MIT
Author: Domen Kozar
Requires-Python: >=3.9,<4.0
Classifier: License :: OSI Approved :: MIT License
Classifier: Programming Language :: Python :: 3
Classifier: Programming Language :: Python :: 3.9
Classifier: Programming Language :: Python :: 3.10
Classifier: Programming Language :: Python :: 3.11
Requires-Dist: click
Requires-Dist: pexpect
